cmlib/__init__.py
cmlib/cmap.py
cmlib/demo.py
cmlib/misc.py
cmlib/version.txt
cmlib/data/readme.txt
cmlib/data/CET/CET-C1.csv
cmlib/data/CET/CET-C1.json
cmlib/data/CET/CET-C2.csv
cmlib/data/CET/CET-C2.json
cmlib/data/CET/CET-C4.csv
cmlib/data/CET/CET-C4.json
cmlib/data/CET/CET-C5.csv
cmlib/data/CET/CET-C5.json
cmlib/data/CET/CET-CBC1.csv
cmlib/data/CET/CET-CBC1.json
cmlib/data/CET/CET-CBC2.csv
cmlib/data/CET/CET-CBC2.json
cmlib/data/CET/CET-CBD1.csv
cmlib/data/CET/CET-CBD1.json
cmlib/data/CET/CET-CBL1.csv
cmlib/data/CET/CET-CBL1.json
cmlib/data/CET/CET-CBL2.csv
cmlib/data/CET/CET-CBL2.json
cmlib/data/CET/CET-CBTC1.csv
cmlib/data/CET/CET-CBTC1.json
cmlib/data/CET/CET-CBTC2.csv
cmlib/data/CET/CET-CBTC2.json
cmlib/data/CET/CET-CBTD1.csv
cmlib/data/CET/CET-CBTD1.json
cmlib/data/CET/CET-CBTl1.csv
cmlib/data/CET/CET-CBTl1.json
cmlib/data/CET/CET-CBTl2.csv
cmlib/data/CET/CET-CBTl2.json
cmlib/data/CET/CET-D1.csv
cmlib/data/CET/CET-D1.json
cmlib/data/CET/CET-D10.csv
cmlib/data/CET/CET-D10.json
cmlib/data/CET/CET-D11.csv
cmlib/data/CET/CET-D11.json
cmlib/data/CET/CET-D12.csv
cmlib/data/CET/CET-D12.json
cmlib/data/CET/CET-D13.csv
cmlib/data/CET/CET-D13.json
cmlib/data/CET/CET-D1A.csv
cmlib/data/CET/CET-D1A.json
cmlib/data/CET/CET-D2.csv
cmlib/data/CET/CET-D2.json
cmlib/data/CET/CET-D3.csv
cmlib/data/CET/CET-D3.json
cmlib/data/CET/CET-D4.csv
cmlib/data/CET/CET-D4.json
cmlib/data/CET/CET-D6.csv
cmlib/data/CET/CET-D6.json
cmlib/data/CET/CET-D7.csv
cmlib/data/CET/CET-D7.json
cmlib/data/CET/CET-D8.csv
cmlib/data/CET/CET-D8.json
cmlib/data/CET/CET-D9.csv
cmlib/data/CET/CET-D9.json
cmlib/data/CET/CET-I1.csv
cmlib/data/CET/CET-I1.json
cmlib/data/CET/CET-I2.csv
cmlib/data/CET/CET-I2.json
cmlib/data/CET/CET-I3.csv
cmlib/data/CET/CET-I3.json
cmlib/data/CET/CET-L1.csv
cmlib/data/CET/CET-L1.json
cmlib/data/CET/CET-L10.csv
cmlib/data/CET/CET-L10.json
cmlib/data/CET/CET-L11.csv
cmlib/data/CET/CET-L11.json
cmlib/data/CET/CET-L12.csv
cmlib/data/CET/CET-L12.json
cmlib/data/CET/CET-L13.csv
cmlib-1.1.3.dist-info/LICENSE
cmlib-1.1.3.dist-info/METADATA
cmlib-1.1.3.dist-info/WHEEL
cmlib-1.1.3.dist-info/entry_points.txt
cmlib-1.1.3.dist-info/top_level.txt
cmlib-1.1.3.dist-info/RECORD
